mcp_django_shell/__init__.py
mcp_django_shell-0.10.0.dist-info/WHEEL
mcp_django_shell-0.10.0.dist-info/METADATA
mcp_django_shell-0.10.0.dist-info/RECORD
