Metadata-Version: 2.3
Name: mcp-django-shell
Version: 0.10.0
Summary: [DEPRECATED - Use mcp-django instead] MCP server providing a stateful Django shell for LLM assistants.
Author: Josh Thomas
Author-email: Josh Thomas <josh@joshthomas.dev>
License: MIT License
Classifier: Development Status :: 7 - Inactive
Classifier: Framework :: Django
Classifier: Framework :: Django :: 4.2
Classifier: Framework :: Django :: 5.1
Classifier: Framework :: Django :: 5.2
Classifier: License :: OSI Approved :: MIT License
Classifier: Operating System :: OS Independent
Classifier: Programming Language :: Python
Classifier: Programming Language :: Python :: 3
Classifier: Programming Language :: Python :: 3 :: Only
Classifier: Programming Language :: Python :: 3.10
Classifier: Programming Language :: Python :: 3.11
Classifier: Programming Language :: Python :: 3.12
Classifier: Programming Language :: Python :: 3.13
Classifier: Programming Language :: Python :: Implementation :: CPython
Requires-Dist: django>4.2
Requires-Dist: fastmcp>=2.11.3
Requires-Dist: mcp-django>=0.1.0,<1.0.0
Requires-Dist: pydantic[email]>=2.11.7
Requires-Python: >=3.10
Project-URL: Documentation, https://github.com/joshuadavidthomas/mcp-django#README
Project-URL: Issues, https://github.com/joshuadavidthomas/mcp-django/issues
Project-URL: Source, https://github.com/joshuadavidthomas/mcp-django
